nemo_library/__init__.py
nemo_library/core.py
nemo_library/version.py
nemo_library/features/__init__.py
nemo_library/features/deficiency_mining.py
nemo_library/features/deprecated.py
nemo_library/features/fileingestion.py
nemo_library/features/focus.py
nemo_library/features/hubspot_handler.py
nemo_library/features/import_configuration.py
nemo_library/features/metadata.py
nemo_library/features/migman_create_project_templates.py
nemo_library/features/migman_database.py
nemo_library/features/migman_delete_projects.py
nemo_library/features/migman_export_data.py
nemo_library/features/migman_load_data.py
nemo_library/features/migman_mapping_apply.py
nemo_library/features/migman_mapping_create.py
nemo_library/features/migman_mapping_load.py
nemo_library/features/migman_precheck_files.py
nemo_library/features/migman_snow_scaper.py
nemo_library/features/nemo_persistence_api.py
nemo_library/features/nemo_report_api.py
nemo_library/features/projects.py
nemo_library/features/shared_api.py
nemo_library/model/__init__.py
nemo_library/model/application.py
nemo_library/model/attribute_group.py
nemo_library/model/attribute_link.py
nemo_library/model/column.py
nemo_library/model/dependency_tree.py
nemo_library/model/diagram.py
nemo_library/model/metric.py
nemo_library/model/migman.py
nemo_library/model/pages.py
nemo_library/model/project.py
nemo_library/model/report.py
nemo_library/model/rule.py
nemo_library/model/subprocess.py
nemo_library/model/tile.py
nemo_library/model/variance.py
nemo_library/templates/__init__.py
nemo_library/templates/migmantemplates.json
nemo_library/ui/__init__.py
nemo_library/ui/ui.py
nemo_library/ui/ui_config_.py
nemo_library/ui/ui_main.py
nemo_library/utils/__init__.py
nemo_library/utils/config.py
nemo_library/utils/migmanutils.py
nemo_library/utils/password_manager.py
nemo_library/utils/utils.py
nemo_library-1.6.62.dist-info/METADATA
nemo_library-1.6.62.dist-info/WHEEL
nemo_library-1.6.62.dist-info/entry_points.txt
nemo_library-1.6.62.dist-info/top_level.txt
nemo_library-1.6.62.dist-info/RECORD
