Metadata-Version: 2.4
Name: nemo_library
Version: 1.6.62
Summary: A Python library for data management, project automation, and integration with the NEMO cloud solution
Author: Gunnar Schug
Author-email: GunnarSchug81@gmail.com
Project-URL: Github, https://github.com/NEMOGunnar/nemo_library
Project-URL: NEMO, https://enter.nemo-ai.com/nemo/
Classifier: Programming Language :: Python :: 3.13
Requires-Dist: pandas
Requires-Dist: requests
Requires-Dist: keyring
Requires-Dist: deprecated
Requires-Dist: openpyxl
Requires-Dist: boto3
Requires-Dist: rapidfuzz
Requires-Dist: lark
Requires-Dist: hubspot
Requires-Dist: hubspot-api-client
Requires-Dist: bs4
Dynamic: author
Dynamic: author-email
Dynamic: classifier
Dynamic: description
Dynamic: description-content-type
Dynamic: project-url
Dynamic: requires-dist
Dynamic: summary
